nosql_storage_wrapper/__init__.py
nosql_storage_wrapper/fs/__init__.py
nosql_storage_wrapper/mongo/__init__.py
nosql_storage_wrapper/mongo/asyn.py
nosql_storage_wrapper/mongo/sync.py
nosql_storage_wrapper/redis/__init__.py
nosql_storage_wrapper-0.1.3.dist-info/LICENSE
nosql_storage_wrapper-0.1.3.dist-info/METADATA
nosql_storage_wrapper-0.1.3.dist-info/WHEEL
nosql_storage_wrapper-0.1.3.dist-info/top_level.txt
nosql_storage_wrapper-0.1.3.dist-info/RECORD
